frappy/__init__.py
frappy/d2.py
frappy/surrogates/__init__.py
frappy/surrogates/surrogates.py
frappy-0.0.2.dist-info/LICENSE.txt
frappy-0.0.2.dist-info/METADATA
frappy-0.0.2.dist-info/WHEEL
frappy-0.0.2.dist-info/top_level.txt
frappy-0.0.2.dist-info/RECORD
