Metadata-Version: 2.1
Name: frappy
Version: 0.0.2
Summary: Python package for non subjectively calculating the correlation dimension from time series data
Author-email: Sandip V George <sandip.varkey@gmail.com>
Project-URL: Homepage, https://github.com/sgeorge91/frappy
Project-URL: Bug Tracker, https://github.com/sgeorge91/frappy/issues
Classifier: Programming Language :: Python :: 3
Classifier: License :: OSI Approved :: GNU General Public License v3 or later (GPLv3+)
Classifier: Operating System :: OS Independent
Requires-Python: >=3.7
License-File: LICENSE.txt
